README.rst
README.txt
bootstrap.py
buildout.cfg
setup.cfg
setup.py
test-plone-3.3.x.cfg
test-plone-4.0.x.cfg
docs/CHANGES.txt
docs/CONTRIBUTORS.txt
docs/INSTALL.txt
docs/LICENSE.GPL
docs/LICENSE.txt
src/babble/__init__.py
src/babble.client.egg-info/PKG-INFO
src/babble.client.egg-info/SOURCES.txt
src/babble.client.egg-info/dependency_links.txt
src/babble.client.egg-info/entry_points.txt
src/babble.client.egg-info/namespace_packages.txt
src/babble.client.egg-info/not-zip-safe
src/babble.client.egg-info/requires.txt
src/babble.client.egg-info/top_level.txt
src/babble/client/__init__.py
src/babble/client/chatroom.py
src/babble/client/config.py
src/babble/client/configure.zcml
src/babble/client/events.py
src/babble/client/index.py
src/babble/client/interfaces.py
src/babble/client/iso8601.py
src/babble/client/tool.py
src/babble/client/utils.py
src/babble/client/version.txt
src/babble/client/browser/__init__.py
src/babble/client/browser/chat.py
src/babble/client/browser/configure.zcml
src/babble/client/browser/interfaces.py
src/babble/client/browser/sharing.py
src/babble/client/browser/viewlets.py
src/babble/client/browser/images/comment_32.png
src/babble/client/browser/stylesheets/chat.css
src/babble/client/browser/templates/chatbox.pt
src/babble/client/browser/templates/chatdata_viewlet.pt
src/babble/client/browser/templates/chatroom_actions.pt
src/babble/client/browser/thirdparty/jquery.ba-dotimeout.js
src/babble/client/browser/thirdparty/jquery.ba-dotimeout.min.js
src/babble/client/browser/thirdparty/jquery.cookie.js
src/babble/client/browser/thirdparty/quicksearch.js
src/babble/client/browser/thirdparty/sha1.js
src/babble/client/exportimport/__init__.py
src/babble/client/exportimport/babblechat_tool.py
src/babble/client/exportimport/configure.zcml
src/babble/client/portlets/__init__.py
src/babble/client/portlets/chatrooms.pt
src/babble/client/portlets/chatrooms.py
src/babble/client/portlets/configure.zcml
src/babble/client/portlets/onlinecontacts.pt
src/babble/client/portlets/onlinecontacts.py
src/babble/client/profiles/default/babblechat_tool.xml
src/babble/client/profiles/default/browserlayer.xml
src/babble/client/profiles/default/catalog.xml
src/babble/client/profiles/default/cssregistry.xml
src/babble/client/profiles/default/jsregistry.xml
src/babble/client/profiles/default/metadata.xml
