Metadata-Version: 1.0
Name: babble.client
Version: 2.0
Summary: Babble: Instant messaging client for Plone
Home-page: http://plone.org/products/babble.client
Author: Syslab.com, JC Brand
Author-email: brand@syslab.com
License: GPL
Keywords: plone syslab.com portlet onlinecontacts
Platform: UNKNOWN
Classifier: Framework :: Plone
Classifier: Programming Language :: Python
